otterwiki/__init__.py
otterwiki/about.md
otterwiki/auth.py
otterwiki/gitstorage.py
otterwiki/help.md
otterwiki/help_admin.md
otterwiki/helper.py
otterwiki/initial_home.md
otterwiki/models.py
otterwiki/pageindex.py
otterwiki/plugins.py
otterwiki/preferences.py
otterwiki/profiler.py
otterwiki/remote.py
otterwiki/renderer.py
otterwiki/renderer_plugins.py
otterwiki/repomgmt.py
otterwiki/server.py
otterwiki/sidebar.py
otterwiki/sitemap.py
otterwiki/tools.py
otterwiki/util.py
otterwiki/version.py
otterwiki/views.py
otterwiki/wiki.py
otterwiki/static/.gitattributes
otterwiki/static/css/.gitattributes
otterwiki/static/css/codemirror-dialog.css
otterwiki/static/css/codemirror-theme.css
otterwiki/static/css/codemirror.css
otterwiki/static/css/fontawesome-all.css
otterwiki/static/css/fontawesome-all.min.css
otterwiki/static/css/halfmoon-variables.css
otterwiki/static/css/halfmoon-variables.min.css
otterwiki/static/css/halfmoon.css
otterwiki/static/css/halfmoon.min.css
otterwiki/static/css/otterwiki.css
otterwiki/static/css/print.css
otterwiki/static/css/pygments-print.css
otterwiki/static/css/pygments.css
otterwiki/static/css/roboto.css
otterwiki/static/css/elements/page.css
otterwiki/static/css/elements/table.css
otterwiki/static/css/elements/toast.css
otterwiki/static/css/partials/documentation.css
otterwiki/static/css/partials/history.css
otterwiki/static/css/partials/sidebar.css
otterwiki/static/custom/custom.css
otterwiki/static/custom/custom.js
otterwiki/static/img/backdrop.jpg
otterwiki/static/img/mermaid-example-dark.svg
otterwiki/static/img/mermaid-example-light.svg
otterwiki/static/img/otter-favicon.ico
otterwiki/static/img/otter-favicon.png
otterwiki/static/img/otter-favicon.xcf
otterwiki/static/img/otter-favicon2.ico
otterwiki/static/img/otter-favicon2.png
otterwiki/static/img/otter-favicon2.xcf
otterwiki/static/img/otter.png
otterwiki/static/img/otter.xcf
otterwiki/static/img/otterhead-100.png
otterwiki/static/img/otterhead.png
otterwiki/static/img/otterhead.xcf
otterwiki-2.17.0.dist-info/licenses/LICENSE
otterwiki-2.17.0.dist-info/METADATA
otterwiki-2.17.0.dist-info/WHEEL
otterwiki-2.17.0.dist-info/top_level.txt
otterwiki-2.17.0.dist-info/RECORD
