Metadata-Version: 2.4
Name: otterwiki
Version: 2.17.0
Summary: An Otter Wiki is Python-based software for collaborative content management, called a wiki. The content is stored in a git repository, which keeps track of all changes. Markdown is used as markup language.
Author-email: Ralph Thesen <mail@redimp.de>
License: MIT License
Project-URL: Homepage, https://otterwiki.com
Project-URL: Github, https://github.com/redimp/otterwiki
Project-URL: Issues, https://github.com/redimp/otterwiki/issues/
Project-URL: Demo, https://demo.otterwiki.com
Keywords: wiki,git,markdown
Classifier: Development Status :: 5 - Production/Stable
Classifier: License :: OSI Approved :: MIT License
Classifier: Programming Language :: Python :: 3
Classifier: Topic :: Internet :: WWW/HTTP :: Dynamic Content
Classifier: Topic :: Internet :: WWW/HTTP :: Dynamic Content :: Wiki
Classifier: Topic :: Internet :: WWW/HTTP :: WSGI :: Application
Classifier: Topic :: Text Processing :: Markup
Classifier: Topic :: Text Processing :: Markup :: Markdown
Classifier: Topic :: Software Development :: Version Control :: Git
Requires-Python: >=3.11
License-File: LICENSE
Requires-Dist: Werkzeug==3.1.5
Requires-Dist: Flask-Login==0.6.3
Requires-Dist: Flask-Mail==0.10.0
Requires-Dist: SQLAlchemy==2.0.36
Requires-Dist: Flask-SQLAlchemy==3.1.1
Requires-Dist: Flask==3.1.1
Requires-Dist: Jinja2==3.1.6
Requires-Dist: gitpython==3.1.44
Requires-Dist: cython==3.0.11
Requires-Dist: mistune==2.0.5
Requires-Dist: pygments==2.18.0
Requires-Dist: Pillow==10.4.0
Requires-Dist: PyYAML==6.0.2
Requires-Dist: unidiff==0.7.5
Requires-Dist: beautifulsoup4==4.12.3
Requires-Dist: pluggy==1.5.0
Requires-Dist: regex==2024.11.6
Requires-Dist: feedgen==1.0.0
Provides-Extra: dev
Requires-Dist: coverage; extra == "dev"
Requires-Dist: pytest; extra == "dev"
Requires-Dist: black; extra == "dev"
Requires-Dist: tox; extra == "dev"
Requires-Dist: tbump; extra == "dev"
Requires-Dist: rjsmin; extra == "dev"
Requires-Dist: git-changelog; extra == "dev"
Requires-Dist: pre-commit; extra == "dev"
Requires-Dist: types-Flask>=1.1.6; extra == "dev"
Dynamic: license-file
